shortwalk/__init__.py
shortwalk/__main__.py
shortwalk-0.0.3.dist-info/LICENSE
shortwalk-0.0.3.dist-info/METADATA
shortwalk-0.0.3.dist-info/WHEEL
shortwalk-0.0.3.dist-info/top_level.txt
shortwalk-0.0.3.dist-info/RECORD
