Metadata-Version: 2.2
Name: shortwalk
Version: 0.0.3
Summary: os.walk with maxdepth option
Home-page: https://github.com/mugiseyebrows/shortwalk
Author: Stanislav Doronin
Author-email: mugisbrows@gmail.com
License-File: LICENSE
Dynamic: author
Dynamic: author-email
Dynamic: description
Dynamic: description-content-type
Dynamic: home-page
Dynamic: summary
